mobio/sdks/dataout/__init__.py
mobio_dataout_sdk-1.0.3.dist-info/METADATA
mobio_dataout_sdk-1.0.3.dist-info/WHEEL
mobio_dataout_sdk-1.0.3.dist-info/top_level.txt
mobio_dataout_sdk-1.0.3.dist-info/RECORD
