Metadata-Version: 2.1
Name: mobio-dataout-sdk
Version: 1.0.3
Summary: Mobio project SDK
Home-page: https://github.com/mobiovn
Author: MOBIO
Author-email: contact@mobio.vn
License: MIT
Keywords: mobio,data out
Requires-Python: >=3.5
Requires-Dist: m-singleton
Requires-Dist: m-kafka-sdk-v2
Requires-Dist: redis
